[{"source":2,"target":10,"type":"t"},{"source":17,"target":16,"type":"s1"},{"source":16,"target":21,"type":"t"},{"source":21,"target":31,"type":"t"},{"source":38,"target":37,"type":"s1"},{"source":37,"target":42,"type":"t"},{"source":42,"target":52,"type":"t"},{"source":59,"target":58,"type":"s1"},{"source":58,"target":63,"type":"t"},{"source":63,"target":73,"type":"t"},{"source":80,"target":79,"type":"s1"},{"source":79,"target":84,"type":"t"},{"source":84,"target":94,"type":"t"},{"source":101,"target":100,"type":"s1"},{"source":100,"target":110,"type":"t"},{"source":0,"target":110,"type":"s1"},{"source":110,"target":114,"type":"t"},{"source":115,"target":114,"type":"s1"},{"source":114,"target":119,"type":"t"},{"source":125,"target":142,"type":"t"},{"source":143,"target":142,"type":"s1"},{"source":119,"target":155,"type":"t"},{"source":161,"target":169,"type":"t"},{"source":161,"target":182,"type":"s1"},{"source":182,"target":186,"type":"t"},{"source":187,"target":186,"type":"s1"},{"source":186,"target":191,"type":"t"},{"source":191,"target":202,"type":"t"},{"source":205,"target":219,"type":"t"},{"source":205,"target":223,"type":"t"},{"source":224,"target":223,"type":"s2"},{"source":225,"target":223,"type":"s1"},{"source":223,"target":229,"type":"t"},{"source":229,"target":236,"type":"t"},{"source":229,"target":240,"type":"t"},{"source":241,"target":240,"type":"s1"},{"source":244,"target":257,"type":"t"},{"source":258,"target":257,"type":"s1"},{"source":161,"target":278,"type":"s1"},{"source":278,"target":282,"type":"t"},{"source":283,"target":282,"type":"s1"},{"source":282,"target":287,"type":"t"},{"source":244,"target":294,"type":"t"},{"source":295,"target":294,"type":"s1"},{"source":287,"target":304,"type":"t"},{"source":129,"target":306,"type":"t"},{"source":129,"target":310,"type":"t"},{"source":311,"target":310,"type":"s1"},{"source":127,"target":320,"type":"t"},{"source":321,"target":320,"type":"s1"},{"source":161,"target":339,"type":"t"},{"source":346,"target":345,"type":"s1"},{"source":345,"target":350,"type":"t"},{"source":351,"target":350,"type":"s1"},{"source":350,"target":355,"type":"t"},{"source":355,"target":362,"type":"t"},{"source":369,"target":368,"type":"s1"},{"source":368,"target":373,"type":"t"},{"source":373,"target":380,"type":"t"},{"source":387,"target":386,"type":"s1"},{"source":386,"target":391,"type":"t"},{"source":392,"target":391,"type":"s1"},{"source":391,"target":396,"type":"t"},{"source":397,"target":396,"type":"s1"},{"source":396,"target":401,"type":"t"},{"source":401,"target":408,"type":"t"},{"source":415,"target":414,"type":"s1"},{"source":414,"target":419,"type":"t"},{"source":419,"target":426,"type":"t"},{"source":433,"target":432,"type":"s1"},{"source":432,"target":437,"type":"t"},{"source":437,"target":444,"type":"t"},{"source":451,"target":450,"type":"s1"},{"source":450,"target":455,"type":"t"},{"source":455,"target":462,"type":"t"},{"source":469,"target":468,"type":"s1"},{"source":468,"target":473,"type":"t"},{"source":474,"target":473,"type":"s1"},{"source":473,"target":478,"type":"t"},{"source":479,"target":478,"type":"s1"},{"source":478,"target":483,"type":"t"},{"source":483,"target":490,"type":"t"},{"source":497,"target":496,"type":"s1"},{"source":496,"target":501,"type":"t"},{"source":501,"target":508,"type":"t"},{"source":515,"target":514,"type":"s1"},{"source":514,"target":519,"type":"t"},{"source":519,"target":526,"type":"t"},{"source":533,"target":532,"type":"s1"},{"source":532,"target":537,"type":"t"},{"source":537,"target":544,"type":"t"},{"source":547,"target":555,"type":"t"},{"source":547,"target":557,"type":"t"},{"source":558,"target":557,"type":"s2"},{"source":559,"target":557,"type":"s1"},{"source":557,"target":561,"type":"t"},{"source":561,"target":582,"type":"t"},{"source":583,"target":582,"type":"s1"},{"source":561,"target":587,"type":"t"},{"source":588,"target":587,"type":"s1"},{"source":561,"target":592,"type":"t"},{"source":593,"target":592,"type":"s1"},{"source":561,"target":597,"type":"t"},{"source":598,"target":597,"type":"s1"},{"source":561,"target":602,"type":"t"},{"source":603,"target":602,"type":"s1"},{"source":561,"target":607,"type":"t"},{"source":608,"target":607,"type":"s1"},{"source":611,"target":618,"type":"t"},{"source":561,"target":622,"type":"t"},{"source":623,"target":622,"type":"s1"},{"source":161,"target":635,"type":"t"},{"source":639,"target":638,"type":"s1"},{"source":638,"target":641,"type":"t"},{"source":642,"target":641,"type":"s1"},{"source":641,"target":644,"type":"t"},{"source":644,"target":648,"type":"t"},{"source":652,"target":651,"type":"s1"},{"source":651,"target":654,"type":"t"},{"source":654,"target":658,"type":"t"},{"source":662,"target":661,"type":"s1"},{"source":661,"target":664,"type":"t"},{"source":665,"target":664,"type":"s1"},{"source":664,"target":667,"type":"t"},{"source":668,"target":667,"type":"s1"},{"source":667,"target":670,"type":"t"},{"source":670,"target":674,"type":"t"},{"source":678,"target":677,"type":"s1"},{"source":677,"target":680,"type":"t"},{"source":680,"target":684,"type":"t"},{"source":688,"target":687,"type":"s1"},{"source":687,"target":690,"type":"t"},{"source":690,"target":694,"type":"t"},{"source":698,"target":697,"type":"s1"},{"source":697,"target":700,"type":"t"},{"source":700,"target":704,"type":"t"},{"source":708,"target":707,"type":"s1"},{"source":707,"target":710,"type":"t"},{"source":711,"target":710,"type":"s1"},{"source":710,"target":713,"type":"t"},{"source":714,"target":713,"type":"s1"},{"source":713,"target":716,"type":"t"},{"source":716,"target":720,"type":"t"},{"source":724,"target":723,"type":"s1"},{"source":723,"target":726,"type":"t"},{"source":726,"target":730,"type":"t"},{"source":734,"target":733,"type":"s1"},{"source":733,"target":736,"type":"t"},{"source":736,"target":740,"type":"t"},{"source":744,"target":743,"type":"s1"},{"source":743,"target":746,"type":"t"},{"source":746,"target":750,"type":"t"},{"source":753,"target":760,"type":"t"},{"source":753,"target":762,"type":"t"},{"source":763,"target":762,"type":"s2"},{"source":764,"target":762,"type":"s1"},{"source":762,"target":766,"type":"t"},{"source":766,"target":781,"type":"t"},{"source":782,"target":781,"type":"s1"},{"source":766,"target":784,"type":"t"},{"source":785,"target":784,"type":"s1"},{"source":766,"target":787,"type":"t"},{"source":788,"target":787,"type":"s1"},{"source":766,"target":790,"type":"t"},{"source":791,"target":790,"type":"s1"},{"source":766,"target":793,"type":"t"},{"source":794,"target":793,"type":"s1"},{"source":766,"target":796,"type":"t"},{"source":797,"target":796,"type":"s1"},{"source":799,"target":803,"type":"t"},{"source":766,"target":807,"type":"t"},{"source":808,"target":807,"type":"s1"},{"source":161,"target":820,"type":"t"},{"source":824,"target":823,"type":"s1"},{"source":823,"target":826,"type":"t"},{"source":827,"target":826,"type":"s1"},{"source":826,"target":829,"type":"t"},{"source":829,"target":833,"type":"t"},{"source":837,"target":836,"type":"s1"},{"source":836,"target":839,"type":"t"},{"source":839,"target":843,"type":"t"},{"source":847,"target":846,"type":"s1"},{"source":846,"target":849,"type":"t"},{"source":850,"target":849,"type":"s1"},{"source":849,"target":852,"type":"t"},{"source":853,"target":852,"type":"s1"},{"source":852,"target":855,"type":"t"},{"source":855,"target":859,"type":"t"},{"source":863,"target":862,"type":"s1"},{"source":862,"target":865,"type":"t"},{"source":865,"target":869,"type":"t"},{"source":873,"target":872,"type":"s1"},{"source":872,"target":875,"type":"t"},{"source":875,"target":879,"type":"t"},{"source":883,"target":882,"type":"s1"},{"source":882,"target":885,"type":"t"},{"source":885,"target":889,"type":"t"},{"source":893,"target":892,"type":"s1"},{"source":892,"target":895,"type":"t"},{"source":896,"target":895,"type":"s1"},{"source":895,"target":898,"type":"t"},{"source":899,"target":898,"type":"s1"},{"source":898,"target":901,"type":"t"},{"source":901,"target":905,"type":"t"},{"source":909,"target":908,"type":"s1"},{"source":908,"target":911,"type":"t"},{"source":911,"target":915,"type":"t"},{"source":919,"target":918,"type":"s1"},{"source":918,"target":921,"type":"t"},{"source":921,"target":925,"type":"t"},{"source":929,"target":928,"type":"s1"},{"source":928,"target":931,"type":"t"},{"source":931,"target":935,"type":"t"},{"source":674,"target":677,"type":"t"},{"source":10,"target":16,"type":"t"},{"source":730,"target":733,"type":"t"},{"source":889,"target":892,"type":"t"},{"source":272,"target":278,"type":"t"},{"source":820,"target":823,"type":"t"},{"source":444,"target":450,"type":"t"},{"source":508,"target":514,"type":"t"},{"source":925,"target":928,"type":"t"},{"source":339,"target":345,"type":"t"},{"source":31,"target":37,"type":"t"},{"source":694,"target":697,"type":"t"},{"source":684,"target":687,"type":"t"},{"source":52,"target":58,"type":"t"},{"source":94,"target":100,"type":"t"},{"source":704,"target":707,"type":"t"},{"source":740,"target":743,"type":"t"},{"source":869,"target":872,"type":"t"},{"source":648,"target":651,"type":"t"},{"source":178,"target":182,"type":"t"},{"source":833,"target":836,"type":"t"},{"source":720,"target":723,"type":"t"},{"source":462,"target":468,"type":"t"},{"source":843,"target":846,"type":"t"},{"source":490,"target":496,"type":"t"},{"source":380,"target":386,"type":"t"},{"source":905,"target":908,"type":"t"},{"source":408,"target":414,"type":"t"},{"source":426,"target":432,"type":"t"},{"source":635,"target":638,"type":"t"},{"source":526,"target":532,"type":"t"},{"source":915,"target":918,"type":"t"},{"source":879,"target":882,"type":"t"},{"source":859,"target":862,"type":"t"},{"source":73,"target":79,"type":"t"},{"source":658,"target":661,"type":"t"},{"source":362,"target":368,"type":"t"}]