{"alphabet": {"size": 3, "declaration": "A,C,B"}, "vertices": [{"num": 0, "actualValue": "A", "incomingEdges": [], "sourceConstraints": [], "timeStamp": 1482521433, "type": 0, "id": 1, "value": "r1!:!getStringValue!!"}, {"num": 0, "actualValue": "A", "incomingEdges": [{"source": 1, "type": "t"}, {"source": 2457, "type": "s1"}, {"source": 2458, "type": "s2"}], "sourceConstraints": [], "timeStamp": 1482521433, "type": 0, "id": 2456, "value": "replace!!CC!:!0"}, {"num": 0, "actualValue": "B", "incomingEdges": [], "sourceConstraints": [], "timeStamp": 1482521433, "type": 0, "id": 2457, "value": "\"B\"!:!<init>"}, {"num": 0, "actualValue": "A", "incomingEdges": [], "sourceConstraints": [], "timeStamp": 1482521433, "type": 0, "id": 2458, "value": "\"A\"!:!<init>"}, {"num": 0, "actualValue": "AA", "incomingEdges": [{"source": 2456, "type": "t"}, {"source": 2460, "type": "s1"}], "sourceConstraints": [], "timeStamp": 1482521433, "type": 0, "id": 2459, "value": "concat!!Ljava/lang/String;!:!0"}, {"num": 0, "actualValue": "A", "incomingEdges": [], "sourceConstraints": [], "timeStamp": 1482521433, "type": 0, "id": 2460, "value": "\"A\"!:!<init>"}, {"num": 0, "actualValue": "AA", "incomingEdges": [{"source": 2456, "type": "t"}, {"source": 2460, "type": "s1"}], "sourceConstraints": [], "timeStamp": 1482521433, "type": 0, "id": 2461, "value": "concat!!Ljava/lang/String;!:!0"}, {"num": 0, "actualValue": "true", "incomingEdges": [{"source": 2461, "type": "t"}, {"source": 2463, "type": "s1"}], "sourceConstraints": [], "timeStamp": 1482521433, "type": 0, "id": 2462, "value": "contains!!Ljava/lang/CharSequence;!:!0"}, {"num": 0, "actualValue": "A", "incomingEdges": [], "sourceConstraints": [], "timeStamp": 1482521433, "type": 0, "id": 2463, "value": "\"A\"!:!<init>"}, {"num": 0, "actualValue": "AA", "incomingEdges": [{"source": 2456, "type": "t"}, {"source": 2460, "type": "s1"}], "sourceConstraints": [], "timeStamp": 1482521433, "type": 0, "id": 2464, "value": "concat!!Ljava/lang/String;!:!0"}, {"num": 0, "actualValue": "false", "incomingEdges": [{"source": 2464, "type": "t"}, {"source": 2466, "type": "s1"}], "sourceConstraints": [], "timeStamp": 1482521433, "type": 0, "id": 2465, "value": "contains!!Ljava/lang/CharSequence;!:!0"}, {"num": 0, "actualValue": "C", "incomingEdges": [], "sourceConstraints": [], "timeStamp": 1482521433, "type": 0, "id": 2466, "value": "\"C\"!:!<init>"}, {"num": 0, "actualValue": "AA", "incomingEdges": [{"source": 2456, "type": "t"}, {"source": 2460, "type": "s1"}], "sourceConstraints": [], "timeStamp": 1482521433, "type": 0, "id": 2467, "value": "concat!!Ljava/lang/String;!:!0"}, {"num": 0, "actualValue": "false", "incomingEdges": [{"source": 2467, "type": "t"}, {"source": 2469, "type": "s1"}], "sourceConstraints": [], "timeStamp": 1482521433, "type": 0, "id": 2468, "value": "contains!!Ljava/lang/CharSequence;!:!0"}, {"num": 0, "actualValue": "B", "incomingEdges": [], "sourceConstraints": [], "timeStamp": 1482521433, "type": 0, "id": 2469, "value": "\"B\"!:!<init>"}, {"num": 0, "actualValue": "AC", "incomingEdges": [{"source": 2456, "type": "t"}, {"source": 2471, "type": "s1"}], "sourceConstraints": [], "timeStamp": 1482521433, "type": 0, "id": 2470, "value": "concat!!Ljava/lang/String;!:!0"}, {"num": 0, "actualValue": "C", "incomingEdges": [], "sourceConstraints": [], "timeStamp": 1482521433, "type": 0, "id": 2471, "value": "\"C\"!:!<init>"}, {"num": 0, "actualValue": "AC", "incomingEdges": [{"source": 2456, "type": "t"}, {"source": 2471, "type": "s1"}], "sourceConstraints": [], "timeStamp": 1482521433, "type": 0, "id": 2472, "value": "concat!!Ljava/lang/String;!:!0"}, {"num": 0, "actualValue": "true", "incomingEdges": [{"source": 2472, "type": "t"}, {"source": 2474, "type": "s1"}], "sourceConstraints": [], "timeStamp": 1482521433, "type": 0, "id": 2473, "value": "contains!!Ljava/lang/CharSequence;!:!0"}, {"num": 0, "actualValue": "A", "incomingEdges": [], "sourceConstraints": [], "timeStamp": 1482521433, "type": 0, "id": 2474, "value": "\"A\"!:!<init>"}, {"num": 0, "actualValue": "AC", "incomingEdges": [{"source": 2456, "type": "t"}, {"source": 2471, "type": "s1"}], "sourceConstraints": [], "timeStamp": 1482521433, "type": 0, "id": 2475, "value": "concat!!Ljava/lang/String;!:!0"}, {"num": 0, "actualValue": "true", "incomingEdges": [{"source": 2475, "type": "t"}, {"source": 2477, "type": "s1"}], "sourceConstraints": [], "timeStamp": 1482521433, "type": 0, "id": 2476, "value": "contains!!Ljava/lang/CharSequence;!:!0"}, {"num": 0, "actualValue": "C", "incomingEdges": [], "sourceConstraints": [], "timeStamp": 1482521433, "type": 0, "id": 2477, "value": "\"C\"!:!<init>"}, {"num": 0, "actualValue": "AC", "incomingEdges": [{"source": 2456, "type": "t"}, {"source": 2471, "type": "s1"}], "sourceConstraints": [], "timeStamp": 1482521433, "type": 0, "id": 2478, "value": "concat!!Ljava/lang/String;!:!0"}, {"num": 0, "actualValue": "false", "incomingEdges": [{"source": 2478, "type": "t"}, {"source": 2480, "type": "s1"}], "sourceConstraints": [], "timeStamp": 1482521433, "type": 0, "id": 2479, "value": "contains!!Ljava/lang/CharSequence;!:!0"}, {"num": 0, "actualValue": "B", "incomingEdges": [], "sourceConstraints": [], "timeStamp": 1482521433, "type": 0, "id": 2480, "value": "\"B\"!:!<init>"}, {"num": 0, "actualValue": "AB", "incomingEdges": [{"source": 2456, "type": "t"}, {"source": 2482, "type": "s1"}], "sourceConstraints": [], "timeStamp": 1482521433, "type": 0, "id": 2481, "value": "concat!!Ljava/lang/String;!:!0"}, {"num": 0, "actualValue": "B", "incomingEdges": [], "sourceConstraints": [], "timeStamp": 1482521433, "type": 0, "id": 2482, "value": "\"B\"!:!<init>"}, {"num": 0, "actualValue": "AB", "incomingEdges": [{"source": 2456, "type": "t"}, {"source": 2482, "type": "s1"}], "sourceConstraints": [], "timeStamp": 1482521433, "type": 0, "id": 2483, "value": "concat!!Ljava/lang/String;!:!0"}, {"num": 0, "actualValue": "true", "incomingEdges": [{"source": 2483, "type": "t"}, {"source": 2485, "type": "s1"}], "sourceConstraints": [], "timeStamp": 1482521433, "type": 0, "id": 2484, "value": "contains!!Ljava/lang/CharSequence;!:!0"}, {"num": 0, "actualValue": "A", "incomingEdges": [], "sourceConstraints": [], "timeStamp": 1482521433, "type": 0, "id": 2485, "value": "\"A\"!:!<init>"}, {"num": 0, "actualValue": "AB", "incomingEdges": [{"source": 2456, "type": "t"}, {"source": 2482, "type": "s1"}], "sourceConstraints": [], "timeStamp": 1482521433, "type": 0, "id": 2486, "value": "concat!!Ljava/lang/String;!:!0"}, {"num": 0, "actualValue": "false", "incomingEdges": [{"source": 2486, "type": "t"}, {"source": 2488, "type": "s1"}], "sourceConstraints": [], "timeStamp": 1482521433, "type": 0, "id": 2487, "value": "contains!!Ljava/lang/CharSequence;!:!0"}, {"num": 0, "actualValue": "C", "incomingEdges": [], "sourceConstraints": [], "timeStamp": 1482521433, "type": 0, "id": 2488, "value": "\"C\"!:!<init>"}, {"num": 0, "actualValue": "AB", "incomingEdges": [{"source": 2456, "type": "t"}, {"source": 2482, "type": "s1"}], "sourceConstraints": [], "timeStamp": 1482521433, "type": 0, "id": 2489, "value": "concat!!Ljava/lang/String;!:!0"}, {"num": 0, "actualValue": "true", "incomingEdges": [{"source": 2489, "type": "t"}, {"source": 2491, "type": "s1"}], "sourceConstraints": [], "timeStamp": 1482521433, "type": 0, "id": 2490, "value": "contains!!Ljava/lang/CharSequence;!:!0"}, {"num": 0, "actualValue": "B", "incomingEdges": [], "sourceConstraints": [], "timeStamp": 1482521433, "type": 0, "id": 2491, "value": "\"B\"!:!<init>"}, {"num": 0, "actualValue": "", "incomingEdges": [{"source": 2456, "type": "t"}, {"source": 2493, "type": "s1"}, {"source": 2494, "type": "s2"}], "sourceConstraints": [], "timeStamp": 1482521433, "type": 0, "id": 2492, "value": "delete!!II!:!0"}, {"num": 0, "actualValue": "0", "incomingEdges": [], "sourceConstraints": [], "timeStamp": 1482521433, "type": 0, "id": 2493, "value": "\"0\"!:!<init>"}, {"num": 0, "actualValue": "0", "incomingEdges": [], "sourceConstraints": [], "timeStamp": 1482521433, "type": 0, "id": 2494, "value": "\"0\"!:!<init>"}, {"num": 0, "actualValue": "", "incomingEdges": [{"source": 2456, "type": "t"}, {"source": 2493, "type": "s1"}, {"source": 2494, "type": "s2"}], "sourceConstraints": [], "timeStamp": 1482521433, "type": 0, "id": 2495, "value": "delete!!II!:!0"}, {"num": 0, "actualValue": "false", "incomingEdges": [{"source": 2495, "type": "t"}, {"source": 2497, "type": "s1"}], "sourceConstraints": [], "timeStamp": 1482521433, "type": 0, "id": 2496, "value": "contains!!Ljava/lang/CharSequence;!:!0"}, {"num": 0, "actualValue": "A", "incomingEdges": [], "sourceConstraints": [], "timeStamp": 1482521433, "type": 0, "id": 2497, "value": "\"A\"!:!<init>"}, {"num": 0, "actualValue": "", "incomingEdges": [{"source": 2456, "type": "t"}, {"source": 2493, "type": "s1"}, {"source": 2494, "type": "s2"}], "sourceConstraints": [], "timeStamp": 1482521433, "type": 0, "id": 2498, "value": "delete!!II!:!0"}, {"num": 0, "actualValue": "false", "incomingEdges": [{"source": 2498, "type": "t"}, {"source": 2500, "type": "s1"}], "sourceConstraints": [], "timeStamp": 1482521433, "type": 0, "id": 2499, "value": "contains!!Ljava/lang/CharSequence;!:!0"}, {"num": 0, "actualValue": "C", "incomingEdges": [], "sourceConstraints": [], "timeStamp": 1482521433, "type": 0, "id": 2500, "value": "\"C\"!:!<init>"}, {"num": 0, "actualValue": "", "incomingEdges": [{"source": 2456, "type": "t"}, {"source": 2493, "type": "s1"}, {"source": 2494, "type": "s2"}], "sourceConstraints": [], "timeStamp": 1482521433, "type": 0, "id": 2501, "value": "delete!!II!:!0"}, {"num": 0, "actualValue": "false", "incomingEdges": [{"source": 2501, "type": "t"}, {"source": 2503, "type": "s1"}], "sourceConstraints": [], "timeStamp": 1482521433, "type": 0, "id": 2502, "value": "contains!!Ljava/lang/CharSequence;!:!0"}, {"num": 0, "actualValue": "B", "incomingEdges": [], "sourceConstraints": [], "timeStamp": 1482521433, "type": 0, "id": 2503, "value": "\"B\"!:!<init>"}, {"num": 0, "actualValue": "", "incomingEdges": [{"source": 2456, "type": "t"}, {"source": 2505, "type": "s1"}, {"source": 2506, "type": "s2"}], "sourceConstraints": [], "timeStamp": 1482521433, "type": 0, "id": 2504, "value": "delete!!II!:!0"}, {"num": 0, "actualValue": "0", "incomingEdges": [], "sourceConstraints": [], "timeStamp": 1482521433, "type": 0, "id": 2505, "value": "\"0\"!:!<init>"}, {"num": 0, "actualValue": "1", "incomingEdges": [], "sourceConstraints": [], "timeStamp": 1482521433, "type": 0, "id": 2506, "value": "\"1\"!:!<init>"}, {"num": 0, "actualValue": "", "incomingEdges": [{"source": 2456, "type": "t"}, {"source": 2505, "type": "s1"}, {"source": 2506, "type": "s2"}], "sourceConstraints": [], "timeStamp": 1482521433, "type": 0, "id": 2507, "value": "delete!!II!:!0"}, {"num": 0, "actualValue": "false", "incomingEdges": [{"source": 2507, "type": "t"}, {"source": 2509, "type": "s1"}], "sourceConstraints": [], "timeStamp": 1482521433, "type": 0, "id": 2508, "value": "contains!!Ljava/lang/CharSequence;!:!0"}, {"num": 0, "actualValue": "A", "incomingEdges": [], "sourceConstraints": [], "timeStamp": 1482521433, "type": 0, "id": 2509, "value": "\"A\"!:!<init>"}, {"num": 0, "actualValue": "", "incomingEdges": [{"source": 2456, "type": "t"}, {"source": 2505, "type": "s1"}, {"source": 2506, "type": "s2"}], "sourceConstraints": [], "timeStamp": 1482521433, "type": 0, "id": 2510, "value": "delete!!II!:!0"}, {"num": 0, "actualValue": "false", "incomingEdges": [{"source": 2510, "type": "t"}, {"source": 2512, "type": "s1"}], "sourceConstraints": [], "timeStamp": 1482521433, "type": 0, "id": 2511, "value": "contains!!Ljava/lang/CharSequence;!:!0"}, {"num": 0, "actualValue": "C", "incomingEdges": [], "sourceConstraints": [], "timeStamp": 1482521433, "type": 0, "id": 2512, "value": "\"C\"!:!<init>"}, {"num": 0, "actualValue": "", "incomingEdges": [{"source": 2456, "type": "t"}, {"source": 2505, "type": "s1"}, {"source": 2506, "type": "s2"}], "sourceConstraints": [], "timeStamp": 1482521433, "type": 0, "id": 2513, "value": "delete!!II!:!0"}, {"num": 0, "actualValue": "false", "incomingEdges": [{"source": 2513, "type": "t"}, {"source": 2515, "type": "s1"}], "sourceConstraints": [], "timeStamp": 1482521433, "type": 0, "id": 2514, "value": "contains!!Ljava/lang/CharSequence;!:!0"}, {"num": 0, "actualValue": "B", "incomingEdges": [], "sourceConstraints": [], "timeStamp": 1482521433, "type": 0, "id": 2515, "value": "\"B\"!:!<init>"}, {"num": 0, "actualValue": "", "incomingEdges": [{"source": 2456, "type": "t"}, {"source": 2517, "type": "s1"}, {"source": 2518, "type": "s2"}], "sourceConstraints": [], "timeStamp": 1482521433, "type": 0, "id": 2516, "value": "delete!!II!:!0"}, {"num": 0, "actualValue": "0", "incomingEdges": [], "sourceConstraints": [], "timeStamp": 1482521433, "type": 0, "id": 2517, "value": "\"0\"!:!<init>"}, {"num": 0, "actualValue": "2", "incomingEdges": [], "sourceConstraints": [], "timeStamp": 1482521433, "type": 0, "id": 2518, "value": "\"2\"!:!<init>"}, {"num": 0, "actualValue": "", "incomingEdges": [{"source": 2456, "type": "t"}, {"source": 2517, "type": "s1"}, {"source": 2518, "type": "s2"}], "sourceConstraints": [], "timeStamp": 1482521433, "type": 0, "id": 2519, "value": "delete!!II!:!0"}, {"num": 0, "actualValue": "false", "incomingEdges": [{"source": 2519, "type": "t"}, {"source": 2521, "type": "s1"}], "sourceConstraints": [], "timeStamp": 1482521433, "type": 0, "id": 2520, "value": "contains!!Ljava/lang/CharSequence;!:!0"}, {"num": 0, "actualValue": "A", "incomingEdges": [], "sourceConstraints": [], "timeStamp": 1482521433, "type": 0, "id": 2521, "value": "\"A\"!:!<init>"}, {"num": 0, "actualValue": "", "incomingEdges": [{"source": 2456, "type": "t"}, {"source": 2517, "type": "s1"}, {"source": 2518, "type": "s2"}], "sourceConstraints": [], "timeStamp": 1482521433, "type": 0, "id": 2522, "value": "delete!!II!:!0"}, {"num": 0, "actualValue": "false", "incomingEdges": [{"source": 2522, "type": "t"}, {"source": 2524, "type": "s1"}], "sourceConstraints": [], "timeStamp": 1482521433, "type": 0, "id": 2523, "value": "contains!!Ljava/lang/CharSequence;!:!0"}, {"num": 0, "actualValue": "C", "incomingEdges": [], "sourceConstraints": [], "timeStamp": 1482521433, "type": 0, "id": 2524, "value": "\"C\"!:!<init>"}, {"num": 0, "actualValue": "", "incomingEdges": [{"source": 2456, "type": "t"}, {"source": 2517, "type": "s1"}, {"source": 2518, "type": "s2"}], "sourceConstraints": [], "timeStamp": 1482521433, "type": 0, "id": 2525, "value": "delete!!II!:!0"}, {"num": 0, "actualValue": "false", "incomingEdges": [{"source": 2525, "type": "t"}, {"source": 2527, "type": "s1"}], "sourceConstraints": [], "timeStamp": 1482521433, "type": 0, "id": 2526, "value": "contains!!Ljava/lang/CharSequence;!:!0"}, {"num": 0, "actualValue": "B", "incomingEdges": [], "sourceConstraints": [], "timeStamp": 1482521433, "type": 0, "id": 2527, "value": "\"B\"!:!<init>"}, {"num": 0, "actualValue": "A", "incomingEdges": [{"source": 2456, "type": "t"}, {"source": 2529, "type": "s1"}, {"source": 2530, "type": "s2"}], "sourceConstraints": [], "timeStamp": 1482521433, "type": 0, "id": 2528, "value": "delete!!II!:!0"}, {"num": 0, "actualValue": "1", "incomingEdges": [], "sourceConstraints": [], "timeStamp": 1482521433, "type": 0, "id": 2529, "value": "\"1\"!:!<init>"}, {"num": 0, "actualValue": "1", "incomingEdges": [], "sourceConstraints": [], "timeStamp": 1482521433, "type": 0, "id": 2530, "value": "\"1\"!:!<init>"}, {"num": 0, "actualValue": "A", "incomingEdges": [{"source": 2456, "type": "t"}, {"source": 2529, "type": "s1"}, {"source": 2530, "type": "s2"}], "sourceConstraints": [], "timeStamp": 1482521433, "type": 0, "id": 2531, "value": "delete!!II!:!0"}, {"num": 0, "actualValue": "true", "incomingEdges": [{"source": 2531, "type": "t"}, {"source": 2533, "type": "s1"}], "sourceConstraints": [], "timeStamp": 1482521433, "type": 0, "id": 2532, "value": "contains!!Ljava/lang/CharSequence;!:!0"}, {"num": 0, "actualValue": "A", "incomingEdges": [], "sourceConstraints": [], "timeStamp": 1482521433, "type": 0, "id": 2533, "value": "\"A\"!:!<init>"}, {"num": 0, "actualValue": "A", "incomingEdges": [{"source": 2456, "type": "t"}, {"source": 2529, "type": "s1"}, {"source": 2530, "type": "s2"}], "sourceConstraints": [], "timeStamp": 1482521433, "type": 0, "id": 2534, "value": "delete!!II!:!0"}, {"num": 0, "actualValue": "false", "incomingEdges": [{"source": 2534, "type": "t"}, {"source": 2536, "type": "s1"}], "sourceConstraints": [], "timeStamp": 1482521433, "type": 0, "id": 2535, "value": "contains!!Ljava/lang/CharSequence;!:!0"}, {"num": 0, "actualValue": "C", "incomingEdges": [], "sourceConstraints": [], "timeStamp": 1482521433, "type": 0, "id": 2536, "value": "\"C\"!:!<init>"}, {"num": 0, "actualValue": "A", "incomingEdges": [{"source": 2456, "type": "t"}, {"source": 2529, "type": "s1"}, {"source": 2530, "type": "s2"}], "sourceConstraints": [], "timeStamp": 1482521433, "type": 0, "id": 2537, "value": "delete!!II!:!0"}, {"num": 0, "actualValue": "false", "incomingEdges": [{"source": 2537, "type": "t"}, {"source": 2539, "type": "s1"}], "sourceConstraints": [], "timeStamp": 1482521433, "type": 0, "id": 2538, "value": "contains!!Ljava/lang/CharSequence;!:!0"}, {"num": 0, "actualValue": "B", "incomingEdges": [], "sourceConstraints": [], "timeStamp": 1482521433, "type": 0, "id": 2539, "value": "\"B\"!:!<init>"}, {"num": 0, "actualValue": "A", "incomingEdges": [{"source": 2456, "type": "t"}, {"source": 2541, "type": "s1"}, {"source": 2542, "type": "s2"}], "sourceConstraints": [], "timeStamp": 1482521433, "type": 0, "id": 2540, "value": "delete!!II!:!0"}, {"num": 0, "actualValue": "1", "incomingEdges": [], "sourceConstraints": [], "timeStamp": 1482521433, "type": 0, "id": 2541, "value": "\"1\"!:!<init>"}, {"num": 0, "actualValue": "2", "incomingEdges": [], "sourceConstraints": [], "timeStamp": 1482521433, "type": 0, "id": 2542, "value": "\"2\"!:!<init>"}, {"num": 0, "actualValue": "A", "incomingEdges": [{"source": 2456, "type": "t"}, {"source": 2541, "type": "s1"}, {"source": 2542, "type": "s2"}], "sourceConstraints": [], "timeStamp": 1482521433, "type": 0, "id": 2543, "value": "delete!!II!:!0"}, {"num": 0, "actualValue": "true", "incomingEdges": [{"source": 2543, "type": "t"}, {"source": 2545, "type": "s1"}], "sourceConstraints": [], "timeStamp": 1482521433, "type": 0, "id": 2544, "value": "contains!!Ljava/lang/CharSequence;!:!0"}, {"num": 0, "actualValue": "A", "incomingEdges": [], "sourceConstraints": [], "timeStamp": 1482521433, "type": 0, "id": 2545, "value": "\"A\"!:!<init>"}, {"num": 0, "actualValue": "A", "incomingEdges": [{"source": 2456, "type": "t"}, {"source": 2541, "type": "s1"}, {"source": 2542, "type": "s2"}], "sourceConstraints": [], "timeStamp": 1482521433, "type": 0, "id": 2546, "value": "delete!!II!:!0"}, {"num": 0, "actualValue": "false", "incomingEdges": [{"source": 2546, "type": "t"}, {"source": 2548, "type": "s1"}], "sourceConstraints": [], "timeStamp": 1482521433, "type": 0, "id": 2547, "value": "contains!!Ljava/lang/CharSequence;!:!0"}, {"num": 0, "actualValue": "C", "incomingEdges": [], "sourceConstraints": [], "timeStamp": 1482521433, "type": 0, "id": 2548, "value": "\"C\"!:!<init>"}, {"num": 0, "actualValue": "A", "incomingEdges": [{"source": 2456, "type": "t"}, {"source": 2541, "type": "s1"}, {"source": 2542, "type": "s2"}], "sourceConstraints": [], "timeStamp": 1482521433, "type": 0, "id": 2549, "value": "delete!!II!:!0"}, {"num": 0, "actualValue": "false", "incomingEdges": [{"source": 2549, "type": "t"}, {"source": 2551, "type": "s1"}], "sourceConstraints": [], "timeStamp": 1482521433, "type": 0, "id": 2550, "value": "contains!!Ljava/lang/CharSequence;!:!0"}, {"num": 0, "actualValue": "B", "incomingEdges": [], "sourceConstraints": [], "timeStamp": 1482521433, "type": 0, "id": 2551, "value": "\"B\"!:!<init>"}, {"num": 0, "actualValue": "A", "incomingEdges": [{"source": 2456, "type": "t"}, {"source": 2553, "type": "s1"}, {"source": 2554, "type": "s2"}], "sourceConstraints": [], "timeStamp": 1482521433, "type": 0, "id": 2552, "value": "delete!!II!:!0"}, {"num": 0, "actualValue": "2", "incomingEdges": [], "sourceConstraints": [], "timeStamp": 1482521433, "type": 0, "id": 2553, "value": "\"2\"!:!<init>"}, {"num": 0, "actualValue": "2", "incomingEdges": [], "sourceConstraints": [], "timeStamp": 1482521433, "type": 0, "id": 2554, "value": "\"2\"!:!<init>"}, {"num": 0, "actualValue": "A", "incomingEdges": [{"source": 2456, "type": "t"}, {"source": 2553, "type": "s1"}, {"source": 2554, "type": "s2"}], "sourceConstraints": [], "timeStamp": 1482521433, "type": 0, "id": 2555, "value": "delete!!II!:!0"}, {"num": 0, "actualValue": "true", "incomingEdges": [{"source": 2555, "type": "t"}, {"source": 2557, "type": "s1"}], "sourceConstraints": [], "timeStamp": 1482521433, "type": 0, "id": 2556, "value": "contains!!Ljava/lang/CharSequence;!:!0"}, {"num": 0, "actualValue": "A", "incomingEdges": [], "sourceConstraints": [], "timeStamp": 1482521433, "type": 0, "id": 2557, "value": "\"A\"!:!<init>"}, {"num": 0, "actualValue": "A", "incomingEdges": [{"source": 2456, "type": "t"}, {"source": 2553, "type": "s1"}, {"source": 2554, "type": "s2"}], "sourceConstraints": [], "timeStamp": 1482521433, "type": 0, "id": 2558, "value": "delete!!II!:!0"}, {"num": 0, "actualValue": "false", "incomingEdges": [{"source": 2558, "type": "t"}, {"source": 2560, "type": "s1"}], "sourceConstraints": [], "timeStamp": 1482521433, "type": 0, "id": 2559, "value": "contains!!Ljava/lang/CharSequence;!:!0"}, {"num": 0, "actualValue": "C", "incomingEdges": [], "sourceConstraints": [], "timeStamp": 1482521433, "type": 0, "id": 2560, "value": "\"C\"!:!<init>"}, {"num": 0, "actualValue": "A", "incomingEdges": [{"source": 2456, "type": "t"}, {"source": 2553, "type": "s1"}, {"source": 2554, "type": "s2"}], "sourceConstraints": [], "timeStamp": 1482521433, "type": 0, "id": 2561, "value": "delete!!II!:!0"}, {"num": 0, "actualValue": "false", "incomingEdges": [{"source": 2561, "type": "t"}, {"source": 2563, "type": "s1"}], "sourceConstraints": [], "timeStamp": 1482521433, "type": 0, "id": 2562, "value": "contains!!Ljava/lang/CharSequence;!:!0"}, {"num": 0, "actualValue": "B", "incomingEdges": [], "sourceConstraints": [], "timeStamp": 1482521433, "type": 0, "id": 2563, "value": "\"B\"!:!<init>"}, {"num": 0, "actualValue": "C", "incomingEdges": [{"source": 2456, "type": "t"}, {"source": 2565, "type": "s1"}, {"source": 2566, "type": "s2"}], "sourceConstraints": [], "timeStamp": 1482521433, "type": 0, "id": 2564, "value": "replace!!CC!:!0"}, {"num": 0, "actualValue": "A", "incomingEdges": [], "sourceConstraints": [], "timeStamp": 1482521433, "type": 0, "id": 2565, "value": "\"A\"!:!<init>"}, {"num": 0, "actualValue": "C", "incomingEdges": [], "sourceConstraints": [], "timeStamp": 1482521433, "type": 0, "id": 2566, "value": "\"C\"!:!<init>"}, {"num": 0, "actualValue": "C", "incomingEdges": [{"source": 2456, "type": "t"}, {"source": 2565, "type": "s1"}, {"source": 2566, "type": "s2"}], "sourceConstraints": [], "timeStamp": 1482521433, "type": 0, "id": 2567, "value": "replace!!CC!:!0"}, {"num": 0, "actualValue": "false", "incomingEdges": [{"source": 2567, "type": "t"}, {"source": 2569, "type": "s1"}], "sourceConstraints": [], "timeStamp": 1482521433, "type": 0, "id": 2568, "value": "contains!!Ljava/lang/CharSequence;!:!0"}, {"num": 0, "actualValue": "A", "incomingEdges": [], "sourceConstraints": [], "timeStamp": 1482521433, "type": 0, "id": 2569, "value": "\"A\"!:!<init>"}, {"num": 0, "actualValue": "C", "incomingEdges": [{"source": 2456, "type": "t"}, {"source": 2565, "type": "s1"}, {"source": 2566, "type": "s2"}], "sourceConstraints": [], "timeStamp": 1482521433, "type": 0, "id": 2570, "value": "replace!!CC!:!0"}, {"num": 0, "actualValue": "true", "incomingEdges": [{"source": 2570, "type": "t"}, {"source": 2572, "type": "s1"}], "sourceConstraints": [], "timeStamp": 1482521433, "type": 0, "id": 2571, "value": "contains!!Ljava/lang/CharSequence;!:!0"}, {"num": 0, "actualValue": "C", "incomingEdges": [], "sourceConstraints": [], "timeStamp": 1482521433, "type": 0, "id": 2572, "value": "\"C\"!:!<init>"}, {"num": 0, "actualValue": "C", "incomingEdges": [{"source": 2456, "type": "t"}, {"source": 2565, "type": "s1"}, {"source": 2566, "type": "s2"}], "sourceConstraints": [], "timeStamp": 1482521433, "type": 0, "id": 2573, "value": "replace!!CC!:!0"}, {"num": 0, "actualValue": "false", "incomingEdges": [{"source": 2573, "type": "t"}, {"source": 2575, "type": "s1"}], "sourceConstraints": [], "timeStamp": 1482521433, "type": 0, "id": 2574, "value": "contains!!Ljava/lang/CharSequence;!:!0"}, {"num": 0, "actualValue": "B", "incomingEdges": [], "sourceConstraints": [], "timeStamp": 1482521433, "type": 0, "id": 2575, "value": "\"B\"!:!<init>"}, {"num": 0, "actualValue": "B", "incomingEdges": [{"source": 2456, "type": "t"}, {"source": 2577, "type": "s1"}, {"source": 2578, "type": "s2"}], "sourceConstraints": [], "timeStamp": 1482521433, "type": 0, "id": 2576, "value": "replace!!CC!:!0"}, {"num": 0, "actualValue": "A", "incomingEdges": [], "sourceConstraints": [], "timeStamp": 1482521433, "type": 0, "id": 2577, "value": "\"A\"!:!<init>"}, {"num": 0, "actualValue": "B", "incomingEdges": [], "sourceConstraints": [], "timeStamp": 1482521433, "type": 0, "id": 2578, "value": "\"B\"!:!<init>"}, {"num": 0, "actualValue": "B", "incomingEdges": [{"source": 2456, "type": "t"}, {"source": 2577, "type": "s1"}, {"source": 2578, "type": "s2"}], "sourceConstraints": [], "timeStamp": 1482521433, "type": 0, "id": 2579, "value": "replace!!CC!:!0"}, {"num": 0, "actualValue": "false", "incomingEdges": [{"source": 2579, "type": "t"}, {"source": 2581, "type": "s1"}], "sourceConstraints": [], "timeStamp": 1482521433, "type": 0, "id": 2580, "value": "contains!!Ljava/lang/CharSequence;!:!0"}, {"num": 0, "actualValue": "A", "incomingEdges": [], "sourceConstraints": [], "timeStamp": 1482521433, "type": 0, "id": 2581, "value": "\"A\"!:!<init>"}, {"num": 0, "actualValue": "B", "incomingEdges": [{"source": 2456, "type": "t"}, {"source": 2577, "type": "s1"}, {"source": 2578, "type": "s2"}], "sourceConstraints": [], "timeStamp": 1482521433, "type": 0, "id": 2582, "value": "replace!!CC!:!0"}, {"num": 0, "actualValue": "false", "incomingEdges": [{"source": 2582, "type": "t"}, {"source": 2584, "type": "s1"}], "sourceConstraints": [], "timeStamp": 1482521433, "type": 0, "id": 2583, "value": "contains!!Ljava/lang/CharSequence;!:!0"}, {"num": 0, "actualValue": "C", "incomingEdges": [], "sourceConstraints": [], "timeStamp": 1482521433, "type": 0, "id": 2584, "value": "\"C\"!:!<init>"}, {"num": 0, "actualValue": "B", "incomingEdges": [{"source": 2456, "type": "t"}, {"source": 2577, "type": "s1"}, {"source": 2578, "type": "s2"}], "sourceConstraints": [], "timeStamp": 1482521433, "type": 0, "id": 2585, "value": "replace!!CC!:!0"}, {"num": 0, "actualValue": "true", "incomingEdges": [{"source": 2585, "type": "t"}, {"source": 2587, "type": "s1"}], "sourceConstraints": [], "timeStamp": 1482521433, "type": 0, "id": 2586, "value": "contains!!Ljava/lang/CharSequence;!:!0"}, {"num": 0, "actualValue": "B", "incomingEdges": [], "sourceConstraints": [], "timeStamp": 1482521433, "type": 0, "id": 2587, "value": "\"B\"!:!<init>"}, {"num": 0, "actualValue": "A", "incomingEdges": [{"source": 2456, "type": "t"}, {"source": 2589, "type": "s1"}, {"source": 2590, "type": "s2"}], "sourceConstraints": [], "timeStamp": 1482521433, "type": 0, "id": 2588, "value": "replace!!CC!:!0"}, {"num": 0, "actualValue": "C", "incomingEdges": [], "sourceConstraints": [], "timeStamp": 1482521433, "type": 0, "id": 2589, "value": "\"C\"!:!<init>"}, {"num": 0, "actualValue": "A", "incomingEdges": [], "sourceConstraints": [], "timeStamp": 1482521433, "type": 0, "id": 2590, "value": "\"A\"!:!<init>"}, {"num": 0, "actualValue": "A", "incomingEdges": [{"source": 2456, "type": "t"}, {"source": 2589, "type": "s1"}, {"source": 2590, "type": "s2"}], "sourceConstraints": [], "timeStamp": 1482521433, "type": 0, "id": 2591, "value": "replace!!CC!:!0"}, {"num": 0, "actualValue": "true", "incomingEdges": [{"source": 2591, "type": "t"}, {"source": 2593, "type": "s1"}], "sourceConstraints": [], "timeStamp": 1482521433, "type": 0, "id": 2592, "value": "contains!!Ljava/lang/CharSequence;!:!0"}, {"num": 0, "actualValue": "A", "incomingEdges": [], "sourceConstraints": [], "timeStamp": 1482521433, "type": 0, "id": 2593, "value": "\"A\"!:!<init>"}, {"num": 0, "actualValue": "A", "incomingEdges": [{"source": 2456, "type": "t"}, {"source": 2589, "type": "s1"}, {"source": 2590, "type": "s2"}], "sourceConstraints": [], "timeStamp": 1482521433, "type": 0, "id": 2594, "value": "replace!!CC!:!0"}, {"num": 0, "actualValue": "false", "incomingEdges": [{"source": 2594, "type": "t"}, {"source": 2596, "type": "s1"}], "sourceConstraints": [], "timeStamp": 1482521433, "type": 0, "id": 2595, "value": "contains!!Ljava/lang/CharSequence;!:!0"}, {"num": 0, "actualValue": "C", "incomingEdges": [], "sourceConstraints": [], "timeStamp": 1482521433, "type": 0, "id": 2596, "value": "\"C\"!:!<init>"}, {"num": 0, "actualValue": "A", "incomingEdges": [{"source": 2456, "type": "t"}, {"source": 2589, "type": "s1"}, {"source": 2590, "type": "s2"}], "sourceConstraints": [], "timeStamp": 1482521433, "type": 0, "id": 2597, "value": "replace!!CC!:!0"}, {"num": 0, "actualValue": "false", "incomingEdges": [{"source": 2597, "type": "t"}, {"source": 2599, "type": "s1"}], "sourceConstraints": [], "timeStamp": 1482521433, "type": 0, "id": 2598, "value": "contains!!Ljava/lang/CharSequence;!:!0"}, {"num": 0, "actualValue": "B", "incomingEdges": [], "sourceConstraints": [], "timeStamp": 1482521433, "type": 0, "id": 2599, "value": "\"B\"!:!<init>"}, {"num": 0, "actualValue": "A", "incomingEdges": [{"source": 2456, "type": "t"}, {"source": 2601, "type": "s1"}, {"source": 2602, "type": "s2"}], "sourceConstraints": [], "timeStamp": 1482521433, "type": 0, "id": 2600, "value": "replace!!CC!:!0"}, {"num": 0, "actualValue": "C", "incomingEdges": [], "sourceConstraints": [], "timeStamp": 1482521433, "type": 0, "id": 2601, "value": "\"C\"!:!<init>"}, {"num": 0, "actualValue": "B", "incomingEdges": [], "sourceConstraints": [], "timeStamp": 1482521433, "type": 0, "id": 2602, "value": "\"B\"!:!<init>"}, {"num": 0, "actualValue": "A", "incomingEdges": [{"source": 2456, "type": "t"}, {"source": 2601, "type": "s1"}, {"source": 2602, "type": "s2"}], "sourceConstraints": [], "timeStamp": 1482521433, "type": 0, "id": 2603, "value": "replace!!CC!:!0"}, {"num": 0, "actualValue": "true", "incomingEdges": [{"source": 2603, "type": "t"}, {"source": 2605, "type": "s1"}], "sourceConstraints": [], "timeStamp": 1482521433, "type": 0, "id": 2604, "value": "contains!!Ljava/lang/CharSequence;!:!0"}, {"num": 0, "actualValue": "A", "incomingEdges": [], "sourceConstraints": [], "timeStamp": 1482521433, "type": 0, "id": 2605, "value": "\"A\"!:!<init>"}, {"num": 0, "actualValue": "A", "incomingEdges": [{"source": 2456, "type": "t"}, {"source": 2601, "type": "s1"}, {"source": 2602, "type": "s2"}], "sourceConstraints": [], "timeStamp": 1482521433, "type": 0, "id": 2606, "value": "replace!!CC!:!0"}, {"num": 0, "actualValue": "false", "incomingEdges": [{"source": 2606, "type": "t"}, {"source": 2608, "type": "s1"}], "sourceConstraints": [], "timeStamp": 1482521433, "type": 0, "id": 2607, "value": "contains!!Ljava/lang/CharSequence;!:!0"}, {"num": 0, "actualValue": "C", "incomingEdges": [], "sourceConstraints": [], "timeStamp": 1482521433, "type": 0, "id": 2608, "value": "\"C\"!:!<init>"}, {"num": 0, "actualValue": "A", "incomingEdges": [{"source": 2456, "type": "t"}, {"source": 2601, "type": "s1"}, {"source": 2602, "type": "s2"}], "sourceConstraints": [], "timeStamp": 1482521433, "type": 0, "id": 2609, "value": "replace!!CC!:!0"}, {"num": 0, "actualValue": "false", "incomingEdges": [{"source": 2609, "type": "t"}, {"source": 2611, "type": "s1"}], "sourceConstraints": [], "timeStamp": 1482521433, "type": 0, "id": 2610, "value": "contains!!Ljava/lang/CharSequence;!:!0"}, {"num": 0, "actualValue": "B", "incomingEdges": [], "sourceConstraints": [], "timeStamp": 1482521433, "type": 0, "id": 2611, "value": "\"B\"!:!<init>"}, {"num": 0, "actualValue": "A", "incomingEdges": [{"source": 2456, "type": "t"}, {"source": 2613, "type": "s1"}, {"source": 2614, "type": "s2"}], "sourceConstraints": [], "timeStamp": 1482521433, "type": 0, "id": 2612, "value": "replace!!CC!:!0"}, {"num": 0, "actualValue": "B", "incomingEdges": [], "sourceConstraints": [], "timeStamp": 1482521433, "type": 0, "id": 2613, "value": "\"B\"!:!<init>"}, {"num": 0, "actualValue": "A", "incomingEdges": [], "sourceConstraints": [], "timeStamp": 1482521433, "type": 0, "id": 2614, "value": "\"A\"!:!<init>"}, {"num": 0, "actualValue": "A", "incomingEdges": [{"source": 2456, "type": "t"}, {"source": 2613, "type": "s1"}, {"source": 2614, "type": "s2"}], "sourceConstraints": [], "timeStamp": 1482521433, "type": 0, "id": 2615, "value": "replace!!CC!:!0"}, {"num": 0, "actualValue": "true", "incomingEdges": [{"source": 2615, "type": "t"}, {"source": 2617, "type": "s1"}], "sourceConstraints": [], "timeStamp": 1482521433, "type": 0, "id": 2616, "value": "contains!!Ljava/lang/CharSequence;!:!0"}, {"num": 0, "actualValue": "A", "incomingEdges": [], "sourceConstraints": [], "timeStamp": 1482521433, "type": 0, "id": 2617, "value": "\"A\"!:!<init>"}, {"num": 0, "actualValue": "A", "incomingEdges": [{"source": 2456, "type": "t"}, {"source": 2613, "type": "s1"}, {"source": 2614, "type": "s2"}], "sourceConstraints": [], "timeStamp": 1482521433, "type": 0, "id": 2618, "value": "replace!!CC!:!0"}, {"num": 0, "actualValue": "false", "incomingEdges": [{"source": 2618, "type": "t"}, {"source": 2620, "type": "s1"}], "sourceConstraints": [], "timeStamp": 1482521433, "type": 0, "id": 2619, "value": "contains!!Ljava/lang/CharSequence;!:!0"}, {"num": 0, "actualValue": "C", "incomingEdges": [], "sourceConstraints": [], "timeStamp": 1482521433, "type": 0, "id": 2620, "value": "\"C\"!:!<init>"}, {"num": 0, "actualValue": "A", "incomingEdges": [{"source": 2456, "type": "t"}, {"source": 2613, "type": "s1"}, {"source": 2614, "type": "s2"}], "sourceConstraints": [], "timeStamp": 1482521433, "type": 0, "id": 2621, "value": "replace!!CC!:!0"}, {"num": 0, "actualValue": "false", "incomingEdges": [{"source": 2621, "type": "t"}, {"source": 2623, "type": "s1"}], "sourceConstraints": [], "timeStamp": 1482521433, "type": 0, "id": 2622, "value": "contains!!Ljava/lang/CharSequence;!:!0"}, {"num": 0, "actualValue": "B", "incomingEdges": [], "sourceConstraints": [], "timeStamp": 1482521433, "type": 0, "id": 2623, "value": "\"B\"!:!<init>"}, {"num": 0, "actualValue": "A", "incomingEdges": [{"source": 2456, "type": "t"}, {"source": 2625, "type": "s1"}, {"source": 2626, "type": "s2"}], "sourceConstraints": [], "timeStamp": 1482521433, "type": 0, "id": 2624, "value": "replace!!CC!:!0"}, {"num": 0, "actualValue": "B", "incomingEdges": [], "sourceConstraints": [], "timeStamp": 1482521433, "type": 0, "id": 2625, "value": "\"B\"!:!<init>"}, {"num": 0, "actualValue": "C", "incomingEdges": [], "sourceConstraints": [], "timeStamp": 1482521433, "type": 0, "id": 2626, "value": "\"C\"!:!<init>"}, {"num": 0, "actualValue": "A", "incomingEdges": [{"source": 2456, "type": "t"}, {"source": 2625, "type": "s1"}, {"source": 2626, "type": "s2"}], "sourceConstraints": [], "timeStamp": 1482521433, "type": 0, "id": 2627, "value": "replace!!CC!:!0"}, {"num": 0, "actualValue": "true", "incomingEdges": [{"source": 2627, "type": "t"}, {"source": 2629, "type": "s1"}], "sourceConstraints": [], "timeStamp": 1482521433, "type": 0, "id": 2628, "value": "contains!!Ljava/lang/CharSequence;!:!0"}, {"num": 0, "actualValue": "A", "incomingEdges": [], "sourceConstraints": [], "timeStamp": 1482521433, "type": 0, "id": 2629, "value": "\"A\"!:!<init>"}, {"num": 0, "actualValue": "A", "incomingEdges": [{"source": 2456, "type": "t"}, {"source": 2625, "type": "s1"}, {"source": 2626, "type": "s2"}], "sourceConstraints": [], "timeStamp": 1482521433, "type": 0, "id": 2630, "value": "replace!!CC!:!0"}, {"num": 0, "actualValue": "false", "incomingEdges": [{"source": 2630, "type": "t"}, {"source": 2632, "type": "s1"}], "sourceConstraints": [], "timeStamp": 1482521433, "type": 0, "id": 2631, "value": "contains!!Ljava/lang/CharSequence;!:!0"}, {"num": 0, "actualValue": "C", "incomingEdges": [], "sourceConstraints": [], "timeStamp": 1482521433, "type": 0, "id": 2632, "value": "\"C\"!:!<init>"}, {"num": 0, "actualValue": "A", "incomingEdges": [{"source": 2456, "type": "t"}, {"source": 2625, "type": "s1"}, {"source": 2626, "type": "s2"}], "sourceConstraints": [], "timeStamp": 1482521433, "type": 0, "id": 2633, "value": "replace!!CC!:!0"}, {"num": 0, "actualValue": "false", "incomingEdges": [{"source": 2633, "type": "t"}, {"source": 2635, "type": "s1"}], "sourceConstraints": [], "timeStamp": 1482521433, "type": 0, "id": 2634, "value": "contains!!Ljava/lang/CharSequence;!:!0"}, {"num": 0, "actualValue": "B", "incomingEdges": [], "sourceConstraints": [], "timeStamp": 1482521433, "type": 0, "id": 2635, "value": "\"B\"!:!<init>"}, {"num": 0, "actualValue": "A", "incomingEdges": [{"source": 1, "type": "t"}, {"source": 2457, "type": "s1"}, {"source": 2458, "type": "s2"}], "sourceConstraints": [], "timeStamp": 1482521433, "type": 0, "id": 2636, "value": "replace!!CC!:!0"}, {"num": 0, "actualValue": "true", "incomingEdges": [{"source": 2636, "type": "t"}, {"source": 2638, "type": "s1"}], "sourceConstraints": [], "timeStamp": 1482521433, "type": 0, "id": 2637, "value": "contains!!Ljava/lang/CharSequence;!:!0"}, {"num": 0, "actualValue": "A", "incomingEdges": [], "sourceConstraints": [], "timeStamp": 1482521433, "type": 0, "id": 2638, "value": "\"A\"!:!<init>"}, {"num": 0, "actualValue": "A", "incomingEdges": [{"source": 1, "type": "t"}, {"source": 2457, "type": "s1"}, {"source": 2458, "type": "s2"}], "sourceConstraints": [], "timeStamp": 1482521433, "type": 0, "id": 2639, "value": "replace!!CC!:!0"}, {"num": 0, "actualValue": "false", "incomingEdges": [{"source": 2639, "type": "t"}, {"source": 2641, "type": "s1"}], "sourceConstraints": [], "timeStamp": 1482521433, "type": 0, "id": 2640, "value": "contains!!Ljava/lang/CharSequence;!:!0"}, {"num": 0, "actualValue": "C", "incomingEdges": [], "sourceConstraints": [], "timeStamp": 1482521433, "type": 0, "id": 2641, "value": "\"C\"!:!<init>"}, {"num": 0, "actualValue": "A", "incomingEdges": [{"source": 1, "type": "t"}, {"source": 2457, "type": "s1"}, {"source": 2458, "type": "s2"}], "sourceConstraints": [], "timeStamp": 1482521433, "type": 0, "id": 2642, "value": "replace!!CC!:!0"}, {"num": 0, "actualValue": "false", "incomingEdges": [{"source": 2642, "type": "t"}, {"source": 2644, "type": "s1"}], "sourceConstraints": [], "timeStamp": 1482521433, "type": 0, "id": 2643, "value": "contains!!Ljava/lang/CharSequence;!:!0"}, {"num": 0, "actualValue": "B", "incomingEdges": [], "sourceConstraints": [], "timeStamp": 1482521433, "type": 0, "id": 2644, "value": "\"B\"!:!<init>"}]}